moneyunify/__init__.py
moneyunify/client.py
tests/__init__.py
tests/test_client.py
moneyunify-0.1.dist-info/METADATA
moneyunify-0.1.dist-info/WHEEL
moneyunify-0.1.dist-info/top_level.txt
moneyunify-0.1.dist-info/RECORD
