Metadata-Version: 2.1
Name: moneyunify
Version: 0.1
Summary: A Python client for the MoneyUnify API to simplify mobile money payments
Home-page: https://github.com/lembani/moneyunify_py
Author: Lembani Sakala
Author-email: lembanisakala@gmail.com
Classifier: Programming Language :: Python :: 3
Classifier: License :: OSI Approved :: MIT License
Classifier: Operating System :: OS Independent
Requires-Python: >=3.6
Requires-Dist: requests >=2.25.1
